{
  "project": "sow-what",
  "sprint": 2,
  "label": "SW S2",
  "phase": "Seed Inventory",
  "hypotheses": [],
  "metrics": {
    "active_session_time_s": 975,
    "active_session_time_display": "16m 15s",
    "total_tokens": 5371469,
    "total_tokens_display": "5.4M",
    "new_work_tokens": 132372,
    "new_work_tokens_display": "132K",
    "cache_hit_rate_pct": 97.5,
    "opus_pct": 100.0,
    "sonnet_pct": 0,
    "haiku_pct": 0,
    "api_calls": 77,
    "subagents": 0,
    "context_compressions": 0,
    "rework_rate": 2.5,
    "tests_total": 79,
    "tests_added": 40,
    "coverage_pct": 95.51,
    "lint_errors": 0,
    "gates_first_pass": false,
    "gates_first_pass_note": "eslint react-hooks/set-state-in-effect rule required refactor; findByText matched multiple elements",
    "loc_added": 1542,
    "loc_added_approx": false,
    "task_type": "feature",
    "judge_score": null,
    "judge_blocked": null,
    "judge_block_reason": null,
    "coderabbit_issues": null,
    "coderabbit_issues_valid": null,
    "mutation_score_pct": null,
    "delegation_ratio_pct": null,
    "orchestrator_tokens": 0,
    "subagent_tokens": 5371469
  }
}
